[
  {
    "address": "0x363f82507Fc3B9A2D978252d4b6369032561FBCE",
    "chainId": 42161,
    "decimals": 8,
    "description": "ETH/USD",
    "feedId": 2,
    "version": "1"
  },
  {
    "address": "0x368bfe8aCaA5b7D9fB5A183A7012E31420b87268",
    "chainId": 42161,
    "decimals": 8,
    "description": "TBTC/USD",
    "feedId": 72,
    "version": "1"
  },
  {
    "address": "0xac4EDD8B5e16422Cd671e85C1D0Fb489B60Ad0A0",
    "chainId": 42161,
    "decimals": 8,
    "description": "USDC/USD",
    "feedId": 54,
    "version": "1"
  },
  {
    "address": "0x9C12c2B16f158b167602cbf06b0FDeD16bfE0eB7",
    "chainId": 42161,
    "decimals": 8,
    "description": "USDe/USD",
    "feedId": 85,
    "version": "1"
  },
  {
    "address": "0x88058266A23CB48c7C63Eca53FC615D8F2F274BA",
    "chainId": 42161,
    "decimals": 8,
    "description": "WBTC/USD",
    "feedId": 83,
    "version": "1"
  },
  {
    "address": "0x0Ac698FE8069a17757eB46C4F70cB4dd679e6330",
    "chainId": 42161,
    "decimals": 18,
    "description": "sUSDe/USDe",
    "feedId": 132,
    "version": "1"
  },
  {
    "address": "0xDC0E6a4372b899b47afCB7e15f4829a94AbceDE9",
    "chainId": 42161,
    "decimals": 8,
    "description": "xUSD/USD",
    "feedId": 146,
    "version": "1"
  },
  {
    "address": "0xBda0c4fADa78997f10C53aFF051d34074A32B9A3",
    "chainId": 42161,
    "decimals": 18,
    "description": "yUSD/USDC",
    "feedId": 160,
    "version": "1"
  }
]