{
  "name": "CrossAdapter",
  "address": "0x3408a0607D39E84D7fF5d5C5C17890B723c2cA41",
  "chainId": 1,
  "base": "0x497C761D268cBC2DB6f40CdB21B9AC019c37917D",
  "cross": "0xcbB7C0000aB88B473b1f5aFd9ef808440eed33Bf",
  "quote": "0x0000000000000000000000000000000000000348",
  "oracleBaseCross": "0xed7287223fF50E2bF1da4D929501E9DdBcF20654",
  "oracleCrossQuote": "0xcE8C42CC7C4F4f5210b49F3E5795B8d3e040A8eb",
  "checks": [
    {
      "id": "Adapter existence",
      "severity": "High",
      "message": "Successfully indexed adapter",
      "pass": true
    },
    {
      "id": "Source code provenance",
      "severity": "High",
      "message": "Contract metadata hash is not recognized.",
      "pass": false
    },
    {
      "id": "Distinct assets",
      "severity": "High",
      "message": "All assets are distinct.",
      "pass": true
    },
    {
      "id": "Consistent asset",
      "severity": "High",
      "message": "Asset 0x497C761D268cBC2DB6f40CdB21B9AC019c37917D is BTCY (BTCY Vault) with 14 decimals.",
      "pass": true
    },
    {
      "id": "Consistent asset",
      "severity": "High",
      "message": "Asset 0x0000000000000000000000000000000000000348 is a special designator address.",
      "pass": true
    },
    {
      "id": "Consistent asset",
      "severity": "High",
      "message": "Asset 0xcbB7C0000aB88B473b1f5aFd9ef808440eed33Bf is cbBTC (Coinbase Wrapped BTC) with 8 decimals.",
      "pass": true
    }
  ],
  "label": "BTCY/cbBTC/USD",
  "methodology": "Unknown",
  "model": "Unknown",
  "provider": "Cross"
}