{
  "name": "PendleUniversalOracle",
  "address": "0x8a9980a8E2053b141Cb5a394f3AE074fEb4aB4a0",
  "chainId": 1,
  "base": "0xeCfaFdC7741323a945A163ed068B5a3C43483957",
  "quote": "0x5086bf358635B81D8C47C66d1C8b9E567Db70c72",
  "pendleMarket": "0x13285bCbc27F92b47B4EDB99D744C07B48C977c0",
  "twapWindow": "900",
  "checks": [
    {
      "id": "Adapter existence",
      "severity": "High",
      "message": "Successfully indexed adapter",
      "pass": true
    },
    {
      "id": "Source code provenance",
      "severity": "High",
      "message": "Contract metadata hash matches a known hash.",
      "pass": true
    },
    {
      "id": "Distinct assets",
      "severity": "High",
      "message": "All assets are distinct.",
      "pass": true
    },
    {
      "id": "Consistent asset",
      "severity": "High",
      "message": "Asset 0xeCfaFdC7741323a945A163ed068B5a3C43483957 is PT-reUSD-10DEC2026 (PT reUSD 10DEC2026) with 6 decimals.",
      "pass": true
    },
    {
      "id": "Consistent asset",
      "severity": "High",
      "message": "Asset 0x5086bf358635B81D8C47C66d1C8b9E567Db70c72 is reUSD (Re Protocol Deposit Token) with 18 decimals.",
      "pass": true
    },
    {
      "id": "Consistent asset",
      "severity": "High",
      "message": "Asset 0x13285bCbc27F92b47B4EDB99D744C07B48C977c0 is PLP-reUSD-10DEC2026 (PLP reUSD 10DEC2026) with 18 decimals.",
      "pass": true
    }
  ],
  "label": "reUSD",
  "methodology": "TWAP",
  "model": "Push",
  "provider": "Pendle"
}